root/__init__.py
root/insurance.py
root/main.py
rootsdk-0.1.3.dist-info/DESCRIPTION.rst
rootsdk-0.1.3.dist-info/METADATA
rootsdk-0.1.3.dist-info/RECORD
rootsdk-0.1.3.dist-info/WHEEL
rootsdk-0.1.3.dist-info/metadata.json
rootsdk-0.1.3.dist-info/top_level.txt
