Metadata-Version: 2.0
Name: rootsdk
Version: 0.1.3
Summary: A python SDK for the Root insurance API
Home-page: https://github.com/BrendanBall/root-insurance-python
Author: Brendan Ball
Author-email: UNKNOWN
License: UNKNOWN
Keywords: root sdk
Platform: UNKNOWN
Classifier: Development Status :: 3 - Alpha
Classifier: Intended Audience :: Developers
Classifier: Topic :: Software Development :: Build Tools
Classifier: License :: OSI Approved :: GNU General Public License v3 or later (GPLv3+)
Classifier: Programming Language :: Python :: 3.6
Requires-Dist: requests
